nba2_interface/__init__.py
nba2_interface/definition.py
nba2_interface/nba1_model_retrieval.py
nba2_interface/nba2_interface.py
nba2_interface/qradar_postgres_connector.py
nba2_interface/route.py
nba2_interface/run_server.py
nba2_interface/singleton.py
nba2liteserver-1.0.1.dist-info/METADATA
nba2liteserver-1.0.1.dist-info/WHEEL
nba2liteserver-1.0.1.dist-info/top_level.txt
nba2liteserver-1.0.1.dist-info/RECORD
