Metadata-Version: 2.1
Name: nba2liteserver
Version: 1.0.1
Summary: NBA2 lite server
Home-page: UNKNOWN
Author: IBM
Author-email: <lalala@gmail.com>
License: UNKNOWN
Platform: UNKNOWN
Classifier: Programming Language :: Python :: 3
Classifier: Operating System :: OS Independent
